varwg/__init__.py
varwg/config_template.py
varwg/ctimes.cpython-313-darwin.so
varwg/ecdf.py
varwg/helpers.py
varwg/sample.met
varwg/smoothing.py
varwg/times.py
varwg/core/__init__.py
varwg/core/base.py
varwg/core/core.py
varwg/core/dyresm_header_template
varwg/core/plotting.py
varwg/core/tests/__init__.py
varwg/core/tests/conftest.py
varwg/core/tests/gen_test_data.py
varwg/core/tests/test_core.py
varwg/meteo/__init__.py
varwg/meteo/avrwind.py
varwg/meteo/brunner.py
varwg/meteo/meteox2y.py
varwg/meteo/meteox2y_cy.cpython-313-darwin.so
varwg/meteo/windrose.py
varwg/test_data/__init__.py
varwg/test_data/air_temperature_tutorial_subset.nc
varwg/test_data/download_fixtures.py
varwg/test_data/freiburg_precipitation_daily_2000_2016.nc
varwg/test_data/konstanz_sun_daily_2000_2016.nc
varwg/test_data/konstanz_temperature_daily_2000_2016.nc
varwg/test_data/stoetten_precipitation_daily_1990_2020.nc
varwg/tests/conftest.py
varwg/tests/test_brunner.py
varwg/tests/test_meteox2y.py
varwg/tests/test_meteoxy_cy.py
varwg/tests/test_readme.py
varwg/tests/test_smoothing.py
varwg/tests/test_thread_local_rng.py
varwg/time_series_analysis/__init__.py
varwg/time_series_analysis/_kde.py
varwg/time_series_analysis/cresample.cpython-313-darwin.so
varwg/time_series_analysis/distributions.py
varwg/time_series_analysis/models.py
varwg/time_series_analysis/optimize.py
varwg/time_series_analysis/phase_randomization.py
varwg/time_series_analysis/rain_stats.py
varwg/time_series_analysis/resample.py
varwg/time_series_analysis/seasonal.py
varwg/time_series_analysis/seasonal_distributions.py
varwg/time_series_analysis/seasonal_kde.py
varwg/time_series_analysis/spectral.py
varwg/time_series_analysis/time_series.py
varwg/time_series_analysis/tests/__init__.py
varwg/time_series_analysis/tests/conftest.py
varwg/time_series_analysis/tests/e1.dat
varwg/time_series_analysis/tests/test_cresample.py
varwg/time_series_analysis/tests/test_distributions.py
varwg/time_series_analysis/tests/test_kde.py
varwg-1.4.6.dist-info/licenses/LICENSE.txt
varwg-1.4.6.dist-info/METADATA
varwg-1.4.6.dist-info/WHEEL
varwg-1.4.6.dist-info/top_level.txt
varwg-1.4.6.dist-info/RECORD
