Metadata-Version: 2.4
Name: varwg
Version: 1.4.6
Summary: A Vector Autoregressive Weather Generator
Author-email: iskur <32363199+iskur@users.noreply.github.com>
License-Expression: BSD-3-Clause
Requires-Python: >=3.13
License-File: LICENSE.txt
Requires-Dist: bottleneck>=1.5.0
Requires-Dist: cartopy>=0.24.1
Requires-Dist: dill>=0.4.0
Requires-Dist: matplotlib>=3.10.3
Requires-Dist: numexpr>=2.11.0
Requires-Dist: pandas>=2.3.0
Requires-Dist: pytz>=2025.2
Requires-Dist: scipy>=1.15.3
Requires-Dist: timezonefinder>=6.5.9
Requires-Dist: tqdm>=4.67.1
Requires-Dist: xarray>=2025.4.0
Dynamic: license-file
